BulkSmsApi/Client.py
BulkSmsApi/Parse.py
BulkSmsApi/__init__.py
Bulksmsapi_zw-1.2.0.dist-info/LICENSE
Bulksmsapi_zw-1.2.0.dist-info/METADATA
Bulksmsapi_zw-1.2.0.dist-info/WHEEL
Bulksmsapi_zw-1.2.0.dist-info/top_level.txt
Bulksmsapi_zw-1.2.0.dist-info/RECORD
