Metadata-Version: 2.1
Name: Bulksmsapi-zw
Version: 1.2.0
Summary: send text messages with bulksmszw api
Home-page: https://github.com/DonnC/BulkSmsZW-Api
Author: Donald Chinhuru
Author-email: donychinhuru@gmail.com
License: MIT
Platform: UNKNOWN
Classifier: License :: OSI Approved :: MIT License
Classifier: Programming Language :: Python :: 3
Classifier: Operating System :: OS Independent
Requires-Dist: requests
